tests/__init__.py
tests/coap_packet_generator.py
tests/launcher.py
tests/test_doctests_common.py
tests/test_analyzer/__init__.py
tests/test_analyzer/test_analyzer.py
tests/test_analyzer/test_conversation.py
tests/test_analyzer/test_node.py
tests/test_analyzer/test_verdict.py
tests/test_dissector/__init__.py
tests/test_dissector/test_capture.py
tests/test_dissector/test_dissect_pcaps.py
tests/test_dissector/test_dissector.py
tests/test_dissector/test_dissector_pcaps_6lowpan.py
tests/test_dissector/test_dissector_pcaps_802154.py
tests/test_dissector/test_dissector_pcaps_coap.py
tests/test_dissector/test_frame.py
tests/test_dumps/__init__.py
tests/test_tat/__init__.py
tests/test_tat/test_common.py
tests/test_tat/test_tat.py
tests/test_tat/test_tat_coap_block.py
tests/test_tat/test_tat_coap_core.py
tests/test_tat/test_tat_coap_observe.py
tests/test_tat/test_webserver.py
tests/test_tools/__init__.py
tests/test_tools/struct_validator.py
tests/test_utils/__init__.py
tests/test_utils/tests.py
tests/test_webserver/__init__.py
tests/test_webserver/tests.py
ttproto/__init__.py
ttproto/__main__.py
ttproto/tat_amqp_interface.py
ttproto/tat_services.py
ttproto/core/__init__.py
ttproto/core/analyzer.py
ttproto/core/clock.py
ttproto/core/control.py
ttproto/core/data.py
ttproto/core/debug.py
ttproto/core/dissector.py
ttproto/core/exceptions.py
ttproto/core/html_logger.py
ttproto/core/list.py
ttproto/core/logger.py
ttproto/core/named.py
ttproto/core/packet.py
ttproto/core/port.py
ttproto/core/primitive.py
ttproto/core/snapshot.py
ttproto/core/subtype.py
ttproto/core/templates.py
ttproto/core/typecheck.py
ttproto/core/typecheck3000.py
ttproto/core/union.py
ttproto/core/xmlgen.py
ttproto/core/lib/__init__.py
ttproto/core/lib/all.py
ttproto/core/lib/encap.py
ttproto/core/lib/ethernet.py
ttproto/core/lib/ieee802154.py
ttproto/core/lib/ieee802154BCKP.py
ttproto/core/lib/ieee802154BCKP2.py
ttproto/core/lib/inet/__init__.py
ttproto-0.1.11.dist-info/METADATA
ttproto-0.1.11.dist-info/RECORD
ttproto-0.1.11.dist-info/WHEEL
ttproto-0.1.11.dist-info/top_level.txt
