Metadata-Version: 2.1
Name: ttproto
Version: 0.1.11
Summary: ttproto is an experimental tool for implementing testingtools, for conformance and interoperability testing mainly.
Home-page: https://www.irisa.fr/tipi/wiki/doku.php/testing_tool_prototype
Author: Univ Rennes / INRIA
Maintainer: Federico Sismondi
Maintainer-email: federico.sismondi@inria.fr
License: CeCILL
Platform: UNKNOWN
Classifier: Development Status :: 3 - Alpha
Classifier: Intended Audience :: Science/Research
Classifier: Intended Audience :: Developers
Classifier: Programming Language :: Python
Classifier: Programming Language :: Python :: 3
Classifier: Programming Language :: Python :: 3.5
Classifier: Programming Language :: Python :: 3.6
Classifier: Topic :: Internet
Classifier: Topic :: Software Development :: Testing
Classifier: Topic :: Scientific/Engineering
Classifier: Operating System :: POSIX
Classifier: Operating System :: Unix
Classifier: Operating System :: MacOS
Requires-Dist: pyyaml
Requires-Dist: requests
Requires-Dist: pika
